commit_message_validator/__init__.py
commit_message_validator/__main__.py
commit_message_validator/cli.py
commit_message_validator/lint.py
commit_message_validator/utils.py
commit_message_validator/version.py
commit_message_validator/validators/__init__.py
commit_message_validator/validators/core.py
commit_message_validator/validators/github.py
commit_message_validator/validators/rules.py
commit_message_validator/validators/wikimedia.py
commit_message_validator-2.1.0.dist-info/METADATA
commit_message_validator-2.1.0.dist-info/WHEEL
commit_message_validator-2.1.0.dist-info/entry_points.txt
commit_message_validator-2.1.0.dist-info/licenses/COPYING
commit_message_validator-2.1.0.dist-info/RECORD
