Metadata-Version: 2.3
Name: commit-message-validator
Version: 2.1.0
Summary: Validate the format of a commit message to Wikimedia Gerrit standards
Project-URL: Documentation, https://www.mediawiki.org/wiki/commit-message-validator
Project-URL: Changelog, https://gitlab.wikimedia.org/repos/ci-tools/commit-message-validator/-/blob/main/HISTORY.rst
Project-URL: Bug tracker, https://phabricator.wikimedia.org/tag/commit-message-validator/
Project-URL: Source code, https://gitlab.wikimedia.org/repos/ci-tools/commit-message-validator
Author-email: Bryan Davis <bd808@wikimedia.org>, Kunal Mehta <Legoktm@debian.org>
Maintainer-email: Bryan Davis <bd808@wikimedia.org>, Kunal Mehta <Legoktm@debian.org>
License-Expression: GPL-2.0-or-later
License-File: COPYING
Keywords: gerrit,git,lint,wikimedia
Classifier: Development Status :: 5 - Production/Stable
Classifier: Environment :: Console
Classifier: Intended Audience :: Developers
Classifier: License :: OSI Approved :: GNU General Public License v2 or later (GPLv2+)
Classifier: Programming Language :: Python
Classifier: Programming Language :: Python :: 3
Classifier: Programming Language :: Python :: 3 :: Only
Classifier: Programming Language :: Python :: 3.6
Classifier: Programming Language :: Python :: 3.7
Classifier: Programming Language :: Python :: 3.8
Classifier: Programming Language :: Python :: 3.9
Classifier: Programming Language :: Python :: 3.10
Classifier: Programming Language :: Python :: 3.11
Classifier: Topic :: Software Development :: Quality Assurance
Classifier: Topic :: Software Development :: Testing
Classifier: Topic :: Software Development :: Version Control :: Git
Requires-Python: >=3.6
Requires-Dist: click-aliases==1.0.4
Requires-Dist: click-option-group==0.5.6
Requires-Dist: click==8.1.7
Requires-Dist: importlib-metadata==6.7.0; python_version < '3.8'
